ytscm/__init__.py
ytscm/event.py
ytscm/monitor.py
ytscm/supporter.py
ytscm-1.0.0.dist-info/LICENSE
ytscm-1.0.0.dist-info/METADATA
ytscm-1.0.0.dist-info/WHEEL
ytscm-1.0.0.dist-info/top_level.txt
ytscm-1.0.0.dist-info/RECORD
