Metadata-Version: 2.1
Name: ytscm
Version: 1.0.0
Summary: A simplified API for live Super Chat monitoring on YouTube.
Home-page: https://github.com/grantwilk/youtube-super-chat-monitor
Author: Grant Wilk
Author-email: grant@remington.pro
License: UNKNOWN
Platform: UNKNOWN
Classifier: Programming Language :: Python :: 3
Classifier: License :: OSI Approved :: GNU General Public License v3 (GPLv3)
Classifier: Operating System :: OS Independent
Requires-Python: >=3.6
